{
	"credit": "Made with Blockbench",
	"textures": {
		"1": "vinery:block/big_bottle",
		"particle": "vinery:block/big_bottle"
	},
	"elements": [
		{
			"from": [6.75, 7, 6.75],
			"to": [8.75, 8.5, 8.75],
			"rotation": {"angle": 0, "axis": "y", "origin": [3.8, 0, 3.2]},
			"faces": {
				"north": {"uv": [7, 7.5, 9, 9], "texture": "#1"},
				"east": {"uv": [9, 7.5, 7, 9], "texture": "#1"},
				"south": {"uv": [7, 7.5, 9, 9], "texture": "#1"},
				"west": {"uv": [9, 7.5, 7, 9], "texture": "#1"},
				"up": {"uv": [7, 7.65, 9, 7.85], "texture": "#1"},
				"down": {"uv": [7, 8.875, 9, 8.625], "texture": "#1"}
			}
		},
		{
			"from": [7.25, 8.5, 7.25],
			"to": [8.25, 10.5, 8.25],
			"rotation": {"angle": 0, "axis": "y", "origin": [3.8, 0, 3.2]},
			"faces": {
				"north": {"uv": [7.5, 5.5, 8.5, 7.5], "texture": "#1"},
				"east": {"uv": [7.5, 5.5, 8.5, 7.5], "texture": "#1"},
				"south": {"uv": [7.5, 5.5, 8.5, 7.5], "texture": "#1"},
				"west": {"uv": [7.5, 5.5, 8.5, 7.5], "texture": "#1"},
				"up": {"uv": [7.5, 5.65, 8.5, 5.85], "texture": "#1"},
				"down": {"uv": [7.5, 7.375, 8.5, 7.125], "texture": "#1"}
			}
		},
		{
			"from": [6.2, 0, 6.2],
			"to": [9.2, 7, 9.2],
			"rotation": {"angle": 0, "axis": "y", "origin": [3.8, 0, 3.2]},
			"faces": {
				"north": {"uv": [6.5, 9, 9.5, 16], "texture": "#1"},
				"east": {"uv": [6.5, 9, 9.5, 16], "texture": "#1"},
				"south": {"uv": [6.5, 9, 9.5, 16], "texture": "#1"},
				"west": {"uv": [6.5, 9, 9.5, 16], "texture": "#1"},
				"up": {"uv": [6.5, 9.15, 9.5, 9.35], "texture": "#1"},
				"down": {"uv": [6.5, 16, 9.5, 16], "texture": "#1"}
			}
		}
	],
	"display": {
		"thirdperson_righthand": {
			"rotation": [39, 45, 0],
			"translation": [0, 2.5, 2]
		},
		"thirdperson_lefthand": {
			"rotation": [39, 45, 0],
			"translation": [0, 2.5, 2]
		},
		"firstperson_righthand": {
			"rotation": [9, 55, 0],
			"translation": [1.5, 2.5, 0]
		},
		"firstperson_lefthand": {
			"rotation": [9, 55, 0],
			"translation": [1.5, 2.5, 0]
		},
		"ground": {
			"translation": [0, 6, 0]
		},
		"gui": {
			"translation": [0, 4, 0],
			"scale": [1.5, 1.5, 1]
		},
		"fixed": {
			"rotation": [-90, 0, 0],
			"translation": [0, 0, -8.25]
		}
	},
	"groups": [
		{
			"name": "Bottle",
			"origin": [3.8, 0, 3.2],
			"color": 0,
			"children": [0, 1, 2]
		}
	]
}