{
	"credit": "Made by Satisfy",
	"textures": {
		"1": "vinery:block/cooking_pot_pipe",
		"3": "vinery:block/red_grapejuice",
		"4": "vinery:block/cooking_pot_red",
		"particle": "vinery:block/cooking_pot_red"
	},
	"elements": [
		{
			"from": [6, 0.5, 6],
			"to": [10, 4, 10],
			"rotation": {"angle": 0, "axis": "y", "origin": [9, 0, 6]},
			"faces": {
				"north": {"uv": [8, 0, 12, 3.5], "texture": "#4"},
				"east": {"uv": [8, 0, 12, 3.5], "texture": "#4"},
				"south": {"uv": [8, 0, 12, 3.5], "texture": "#4"},
				"west": {"uv": [4, 0, 8, 3.5], "texture": "#4"},
				"up": {"uv": [11, 10, 2, 1], "texture": "#3"},
				"down": {"uv": [4, 4, 0, 8], "texture": "#missing"}
			}
		},
		{
			"from": [6, 4, 6],
			"to": [6.5, 4.75, 10],
			"rotation": {"angle": 0, "axis": "y", "origin": [9, 0, 6]},
			"faces": {
				"north": {"uv": [11, 12, 11.5, 13], "texture": "#4"},
				"east": {"uv": [7.5, 9, 11.5, 10], "texture": "#4"},
				"south": {"uv": [12, 12, 12.5, 13], "texture": "#4"},
				"west": {"uv": [7, 9, 11, 10], "texture": "#4"},
				"up": {"uv": [5.5, 15, 5, 11], "texture": "#4"},
				"down": {"uv": [5.5, 11, 5, 15], "texture": "#4"}
			}
		},
		{
			"from": [6.25, 3.75, 5],
			"to": [6.75, 4.5, 6],
			"rotation": {"angle": 0, "axis": "y", "origin": [9, 0, 6]},
			"faces": {
				"north": {"uv": [0, 13, 0.5, 14], "texture": "#4"},
				"east": {"uv": [3, 12, 4, 13], "texture": "#4"},
				"south": {"uv": [1, 13, 1.5, 14], "texture": "#4"},
				"west": {"uv": [12, 3, 13, 4], "texture": "#4"},
				"up": {"uv": [2.5, 14, 2, 13], "texture": "#4"},
				"down": {"uv": [3.5, 13, 3, 14], "texture": "#4"}
			}
		},
		{
			"from": [6.25, 3.75, 10],
			"to": [6.75, 4.5, 11],
			"rotation": {"angle": 0, "axis": "y", "origin": [9, 0, 6]},
			"faces": {
				"north": {"uv": [13, 3, 13.5, 4], "texture": "#4"},
				"east": {"uv": [12, 4, 13, 5], "texture": "#4"},
				"south": {"uv": [13, 4, 13.5, 5], "texture": "#4"},
				"west": {"uv": [12, 6, 13, 7], "texture": "#4"},
				"up": {"uv": [13.5, 6, 13, 5], "texture": "#4"},
				"down": {"uv": [13.5, 6, 13, 7], "texture": "#4"}
			}
		},
		{
			"from": [9.25, 3.75, 5],
			"to": [9.75, 4.5, 6],
			"rotation": {"angle": 0, "axis": "y", "origin": [9, 0, 6]},
			"faces": {
				"north": {"uv": [8, 13, 8.5, 14], "texture": "#4"},
				"east": {"uv": [12, 6, 13, 7], "texture": "#4"},
				"south": {"uv": [9, 13, 9.5, 14], "texture": "#4"},
				"west": {"uv": [8, 12, 9, 13], "texture": "#4"},
				"up": {"uv": [13.5, 10, 13, 9], "texture": "#4"},
				"down": {"uv": [10.5, 13, 10, 14], "texture": "#4"}
			}
		},
		{
			"from": [9.25, 3.75, 10],
			"to": [9.75, 4.5, 11],
			"rotation": {"angle": 0, "axis": "y", "origin": [9, 0, 6]},
			"faces": {
				"north": {"uv": [13, 10, 13.5, 11], "texture": "#4"},
				"east": {"uv": [13, 3, 12, 4], "texture": "#4"},
				"south": {"uv": [11, 13, 11.5, 14], "texture": "#4"},
				"west": {"uv": [10, 12, 11, 13], "texture": "#4"},
				"up": {"uv": [12.5, 14, 12, 13], "texture": "#4"},
				"down": {"uv": [13.5, 12, 13, 13], "texture": "#4"}
			}
		},
		{
			"from": [6.5, 4, 6],
			"to": [9.5, 4.75, 6.5],
			"rotation": {"angle": 0, "axis": "y", "origin": [9, 0, 6]},
			"faces": {
				"north": {"uv": [8, 7, 11, 8], "texture": "#4"},
				"east": {"uv": [13, 13, 13.5, 14], "texture": "#4"},
				"south": {"uv": [8, 8, 11, 9], "texture": "#4"},
				"west": {"uv": [0, 14, 0.5, 15], "texture": "#4"},
				"up": {"uv": [14, 7.5, 11, 7], "texture": "#4"},
				"down": {"uv": [11, 11, 8, 11.5], "texture": "#4"}
			}
		},
		{
			"from": [6.75, 3.75, 5],
			"to": [9.25, 4.5, 5.5],
			"rotation": {"angle": 0, "axis": "y", "origin": [9, 0, 6]},
			"faces": {
				"north": {"uv": [4, 10, 6.5, 11], "texture": "#4"},
				"east": {"uv": [1, 14, 1.5, 15], "texture": "#4"},
				"south": {"uv": [7, 10, 9.5, 11], "texture": "#4"},
				"west": {"uv": [2, 14, 2.5, 15], "texture": "#4"},
				"up": {"uv": [2.5, 12.5, 0, 12], "texture": "#4"},
				"down": {"uv": [14.5, 0, 12, 0.5], "texture": "#4"}
			}
		},
		{
			"from": [6.75, 3.75, 10.5],
			"to": [9.25, 4.5, 11],
			"rotation": {"angle": 0, "axis": "y", "origin": [9, 0, 6]},
			"faces": {
				"north": {"uv": [10, 9, 12.5, 10], "texture": "#4"},
				"east": {"uv": [3, 14, 3.5, 15], "texture": "#4"},
				"south": {"uv": [4, 10, 6.5, 11], "texture": "#4"},
				"west": {"uv": [14, 3, 14.5, 4], "texture": "#4"},
				"up": {"uv": [14.5, 1.5, 12, 1], "texture": "#4"},
				"down": {"uv": [14.5, 2, 12, 2.5], "texture": "#4"}
			}
		},
		{
			"from": [6.5, 4, 9.5],
			"to": [9.5, 4.75, 10],
			"rotation": {"angle": 0, "axis": "y", "origin": [9, 0, 6]},
			"faces": {
				"north": {"uv": [4, 9, 7, 10], "texture": "#4"},
				"east": {"uv": [14, 4, 14.5, 5], "texture": "#4"},
				"south": {"uv": [8.5, 4, 11.5, 5], "texture": "#4"},
				"west": {"uv": [14, 5, 14.5, 6], "texture": "#4"},
				"up": {"uv": [14, 8.5, 11, 8], "texture": "#4"},
				"down": {"uv": [14, 11, 11, 11.5], "texture": "#4"}
			}
		},
		{
			"from": [9, 2.03934, 6.55276],
			"to": [9.5, 7.03934, 7.05276],
			"rotation": {"angle": 0, "axis": "y", "origin": [9.75, 4.53934, 6.80276]},
			"faces": {
				"north": {"uv": [0, 0, 1, 10], "texture": "#1"},
				"east": {"uv": [1, 0, 2, 10], "texture": "#1"},
				"south": {"uv": [2, 0, 3, 10], "texture": "#1"},
				"west": {"uv": [3, 0, 4, 10], "texture": "#1"},
				"up": {"uv": [5, 1, 4, 0], "texture": "#1"},
				"down": {"uv": [5, 1, 4, 2], "texture": "#1"}
			}
		},
		{
			"from": [9.5, 4, 6],
			"to": [10, 4.75, 10],
			"rotation": {"angle": 0, "axis": "y", "origin": [9, 0, 6]},
			"faces": {
				"north": {"uv": [14, 6, 14.5, 7], "texture": "#4"},
				"east": {"uv": [8, 4, 12, 5], "texture": "#4"},
				"south": {"uv": [14, 7, 14.5, 8], "texture": "#4"},
				"west": {"uv": [8, 4, 12, 5], "texture": "#4"},
				"up": {"uv": [6.5, 15, 6, 11], "texture": "#4"},
				"down": {"uv": [7.5, 11, 7, 15], "texture": "#4"}
			}
		}
	],
	"groups": [
		{
			"name": "bone",
			"origin": [9, 0, 6],
			"color": 0,
			"children": [
				0,
				{
					"name": "bone2",
					"origin": [9, 0, 6],
					"color": 0,
					"children": [1, 2, 3, 4, 5, 6, 7, 8, 9, 10]
				},
				11
			]
		}
	]
}