{
  "parent": "minecraft:recipes/root",
  "rewards": {
    "recipes": [
      "vinery:chair"
    ]
  },
  "criteria": {
    "has_grass_block": {
      "trigger": "minecraft:inventory_changed",
      "conditions": {
        "items": [
          {
            "items": [
              "minecraft:spruce_slab"
            ]
          }
        ]
      }
    },
    "has_the_recipe": {
      "trigger": "minecraft:recipe_unlocked",
      "conditions": {
        "recipe": "vinery:chair"
      }
    }
  },
  "requirements": [
    [
      "has_chair",
      "has_the_recipe"
    ]
  ]
}